metadata_driver_arweave/__init__.py
metadata_driver_arweave/arweave_client.py
metadata_driver_arweave/plugin.py
nevermined_metadata_driver_arweave-0.1.4.dist-info/METADATA
nevermined_metadata_driver_arweave-0.1.4.dist-info/WHEEL
nevermined_metadata_driver_arweave-0.1.4.dist-info/top_level.txt
nevermined_metadata_driver_arweave-0.1.4.dist-info/RECORD
