Metadata-Version: 2.1
Name: nevermined-metadata-driver-arweave
Version: 0.1.4
Summary: 🐳 Metadata Arweave Driver (Python).
Home-page: https://github.com/nevermined-io/metadata-driver-arweave
Author: nevermined-io
Author-email: root@nevermined.io
License: Apache Software License 2.0
Keywords: nevermined-metadata-driver-arweave
Platform: UNKNOWN
Classifier: Development Status :: 2 - Pre-Alpha
Classifier: Intended Audience :: Developers
Classifier: License :: OSI Approved :: Apache Software License
Classifier: Natural Language :: English
Classifier: Programming Language :: Python :: 3.4
Classifier: Programming Language :: Python :: 3.5
Classifier: Programming Language :: Python :: 3.6
Requires-Dist: nevermined-metadata-driver-interface (>=0.2.0)
Requires-Dist: arweave-python-client (>=1.0.18)
Provides-Extra: dev
Requires-Dist: pytest ; extra == 'dev'
Provides-Extra: test
Requires-Dist: pytest ; extra == 'test'
